{"mc":{
	"115_zixiaxianzi_s":{
		"frameRate":24,
		"labels":[
			{"name":"skill_1","frame":1,"end":35}
			
			],
		"events":[
			
			],
		"frames":[
			
			{
			"res":"151EBC2",
			"x":-22,
			"y":-69
			},
			{
			"res":"DA8084C6",
			"x":-25,
			"y":-69
			},
			{
			"res":"91D06D7F",
			"x":-28,
			"y":-69
			},
			{
			"res":"AA3B4F8A",
			"x":-30,
			"y":-69
			},
			{
			"res":"5BE4B301",
			"x":-33,
			"y":-69
			},
			{
			"res":"85095C4",
			"x":-21,
			"y":-107
			},
			{
			"res":"CFE9F413",
			"x":-26,
			"y":-151
			},
			{
			"res":"C76C371C",
			"x":-37,
			"y":-195
			},
			{
			"res":"8E2147FD",
			"x":-32,
			"y":-197
			},
			{
			"res":"B504DCA3",
			"x":-31,
			"y":-199
			},
			{
			"res":"98F02B08",
			"x":-31,
			"y":-200
			},
			{
			"res":"522B8031",
			"x":-30,
			"y":-202
			},
			{
			"res":"134C5B7A",
			"x":-30,
			"y":-205
			},
			{
			"res":"563D2727",
			"x":-29,
			"y":-209
			},
			{
			"res":"C4471A1E",
			"x":-28,
			"y":-212
			},
			{
			"res":"8FC52166",
			"x":-27,
			"y":-215
			},
			{
			"res":"44FD9AAA",
			"x":-27,
			"y":-217,
			"duration":3
			},
			{
			"res":"406F512A",
			"x":-52,
			"y":-228
			},
			{
			"res":"D13C5A7C",
			"x":-55,
			"y":-219
			},
			{
			"res":"89A86E44",
			"x":-60,
			"y":-198
			},
			{
			"res":"FB037500",
			"x":-97,
			"y":-182
			},
			{
			"res":"70C65EB3",
			"x":-113,
			"y":-182
			},
			{
			"res":"8F432CDF",
			"x":-124,
			"y":-182
			},
			{
			"res":"4B29F28F",
			"x":0,
			"y":-171
			},
			{
			"res":"B922E67",
			"x":-4,
			"y":-160
			},
			{
			"res":"1A1A7D39",
			"x":-9,
			"y":-149
			},
			{
			"res":"9ABE30B2",
			"x":-14,
			"y":-137
			},
			{
			"res":"3690CA57",
			"x":-18,
			"y":-126
			},
			{
			"res":"5BE4B301",
			"x":-33,
			"y":-69
			},
			{
			"res":"1E6701C2",
			"x":-31,
			"y":-69
			},
			{
			"res":"698A4369",
			"x":-28,
			"y":-69
			},
			{
			"res":"4661D1D6",
			"x":-25,
			"y":-69
			},
			{
			"res":"151EBC2",
			"x":-22,
			"y":-69
			}
			]
}},
	"res":{
		"8FC52166":{"x":567,"y":151,"w":78,"h":80},
		"44FD9AAA":{"x":85,"y":148,"w":80,"h":81},
		"DA8084C6":{"x":796,"y":257,"w":69,"h":71},
		"8E2147FD":{"x":906,"y":255,"w":67,"h":74},
		"C4471A1E":{"x":647,"y":151,"w":76,"h":79},
		"1E6701C2":{"x":0,"y":229,"w":73,"h":71},
		"89A86E44":{"x":418,"y":115,"w":147,"h":125},
		"D13C5A7C":{"x":743,"y":0,"w":141,"h":140},
		"698A4369":{"x":567,"y":233,"w":71,"h":71},
		"563D2727":{"x":829,"y":178,"w":75,"h":77},
		"1A1A7D39":{"x":886,"y":96,"w":83,"h":80},
		"4661D1D6":{"x":241,"y":300,"w":69,"h":71},
		"AA3B4F8A":{"x":647,"y":232,"w":72,"h":71},
		"134C5B7A":{"x":906,"y":178,"w":74,"h":75},
		"406F512A":{"x":605,"y":0,"w":136,"h":149},
		"522B8031":{"x":167,"y":227,"w":72,"h":73},
		"151EBC2":{"x":0,"y":302,"w":66,"h":70},
		"B922E67":{"x":0,"y":148,"w":83,"h":79},
		"9ABE30B2":{"x":743,"y":142,"w":84,"h":79},
		"4B29F28F":{"x":215,"y":146,"w":84,"h":79},
		"C76C371C":{"x":75,"y":231,"w":70,"h":74},
		"CFE9F413":{"x":725,"y":223,"w":69,"h":80},
		"85095C4":{"x":886,"y":0,"w":72,"h":94},
		"98F02B08":{"x":317,"y":227,"w":71,"h":73},
		"3690CA57":{"x":301,"y":146,"w":83,"h":79},
		"70C65EB3":{"x":215,"y":0,"w":201,"h":144},
		"B504DCA3":{"x":463,"y":242,"w":68,"h":73},
		"8F432CDF":{"x":0,"y":0,"w":213,"h":146},
		"FB037500":{"x":418,"y":0,"w":185,"h":113},
		"5BE4B301":{"x":241,"y":227,"w":74,"h":71},
		"91D06D7F":{"x":390,"y":242,"w":71,"h":71}
	}}