{"mc":{
	"131_skill_1_source":{
		"frameRate":24,
		"events":[
			
			],
		"frames":[
			
			{
			"res":"FAB07629",
			"x":-80,
			"y":-103
			},
			{
			"res":"9D183CA8",
			"x":-77,
			"y":-100
			},
			{
			"res":"E344C5AD",
			"x":-69,
			"y":-101
			},
			{
			"res":"CC031C8",
			"x":-59,
			"y":-98
			},
			{
			"res":"F8C824D2",
			"x":-47,
			"y":-96
			},
			{
			"res":"E7A8D91F",
			"x":-43,
			"y":-90
			},
			{
			"res":"6C316D3E",
			"x":-36,
			"y":-84
			},
			{
			"res":"E8537496",
			"x":-37,
			"y":-81
			},
			{
			"res":"752ACA43",
			"x":-43,
			"y":-102
			},
			{
			"res":"B00227A3",
			"x":-63,
			"y":-692
			},
			{
			"res":"D04BF5DD",
			"x":-64,
			"y":-692
			},
			{
			"res":"C3588E80",
			"x":-66,
			"y":-692
			},
			{
			"res":"4895B5E1",
			"x":-78,
			"y":-692
			},
			{
			"res":"471FF637",
			"x":-82,
			"y":-692
			},
			{
			"res":"F2294227",
			"x":-92,
			"y":-692
			},
			{
			"res":"46FF35F9",
			"x":-79,
			"y":-692
			},
			{
			"res":"A8D41BF",
			"x":-50,
			"y":-692
			},
			{
			"res":"81E567D6",
			"x":-56,
			"y":-692
			},
			{
			"res":"8F4EF581",
			"x":-55,
			"y":-692
			},
			{
			"res":"C531D4C7",
			"x":-19,
			"y":-692,
			"duration":2
			},
			{
			"res":"C8845EF4",
			"x":-19,
			"y":-692
			},
			{
			"res":"8F949DC4",
			"x":-17,
			"y":-692
			},
			{
			"res":"183C6100",
			"x":-17,
			"y":-692
			},
			{
			"res":"2505E484",
			"x":-14,
			"y":-692
			}
			]
}},
	"res":{
		"C531D4C7":{"x":364,"y":721,"w":42,"h":697},
		"FAB07629":{"x":0,"y":750,"w":169,"h":137},
		"E7A8D91F":{"x":238,"y":1012,"w":99,"h":116},
		"D04BF5DD":{"x":790,"y":0,"w":115,"h":715},
		"8F4EF581":{"x":669,"y":720,"w":92,"h":706},
		"46FF35F9":{"x":364,"y":0,"w":163,"h":719},
		"F8C824D2":{"x":127,"y":1012,"w":109,"h":128},
		"B00227A3":{"x":907,"y":0,"w":113,"h":710},
		"81E567D6":{"x":790,"y":717,"w":94,"h":709},
		"F2294227":{"x":0,"y":0,"w":194,"h":748},
		"8F949DC4":{"x":452,"y":721,"w":39,"h":696},
		"CC031C8":{"x":0,"y":889,"w":125,"h":133},
		"752ACA43":{"x":569,"y":723,"w":82,"h":127},
		"A8D41BF":{"x":907,"y":712,"w":94,"h":710},
		"471FF637":{"x":196,"y":0,"w":166,"h":730},
		"C8845EF4":{"x":408,"y":721,"w":42,"h":697},
		"E344C5AD":{"x":171,"y":871,"w":146,"h":139},
		"E8537496":{"x":569,"y":955,"w":76,"h":102},
		"183C6100":{"x":493,"y":723,"w":39,"h":696},
		"4895B5E1":{"x":529,"y":0,"w":138,"h":721},
		"9D183CA8":{"x":196,"y":732,"w":162,"h":137},
		"2505E484":{"x":534,"y":723,"w":33,"h":696},
		"6C316D3E":{"x":569,"y":852,"w":84,"h":101},
		"C3588E80":{"x":669,"y":0,"w":119,"h":718}
	}}